DistilTag/__init__.py
DistilTag/download.py
DistilTag/tagger.py
DistilTag-0.2.2.dist-info/LICENSE
DistilTag-0.2.2.dist-info/METADATA
DistilTag-0.2.2.dist-info/WHEEL
DistilTag-0.2.2.dist-info/top_level.txt
DistilTag-0.2.2.dist-info/RECORD
